setup.cfg
setup.py
segment_source_resource/__init__.py
segment_source_resource/exceptions.py
segment_source_resource/resource.py
segment_source_resource/sync.py
segment_source_resource.egg-info/PKG-INFO
segment_source_resource.egg-info/SOURCES.txt
segment_source_resource.egg-info/dependency_links.txt
segment_source_resource.egg-info/requires.txt
segment_source_resource.egg-info/top_level.txt