Metadata-Version: 1.0
Name: segment-source-resource
Version: 0.10.0
Summary: Abstraction to make sources easier to write
Home-page: https://github.com/segmentio/python-source-resource
Author: Segment
Author-email: friends@segment.com
License: UNKNOWN
Platform: UNKNOWN
